pybitrot/__init__.py
pybitrot/__version__.py
pybitrot/pybitrot.py
pybitrot-0.1.0.dist-info/LICENSE
pybitrot-0.1.0.dist-info/METADATA
pybitrot-0.1.0.dist-info/WHEEL
pybitrot-0.1.0.dist-info/top_level.txt
pybitrot-0.1.0.dist-info/RECORD
