Metadata-Version: 2.1
Name: pybitrot
Version: 0.1.0
Summary: Bits rotation module.
Home-page: https://github.com/lzutao/pybitrot
Author: Lzu Tao
Author-email: lzutao@gmail.com
License: MIT
Platform: UNKNOWN
Classifier: License :: OSI Approved :: MIT License
Classifier: Programming Language :: Python
Classifier: Programming Language :: Python :: 3
Classifier: Programming Language :: Python :: 3.6
Classifier: Programming Language :: Python :: Implementation :: CPython
Classifier: Programming Language :: Python :: Implementation :: PyPy
Requires-Python: >=2.7.0
